jupyter2hashnode/__init__.py
jupyter2hashnode/__main__.py
jupyter2hashnode/cli.py
jupyter2hashnode/examples/_drafts.ipynb
jupyter2hashnode/examples/example.ipynb
jupyter2hashnode/examples/jupyter2hashnode_story.ipynb
jupyter2hashnode/examples/plot_digits_classification.ipynb
jupyter2hashnode/hashnode.py
jupyter2hashnode/jupyter2hashnode.py
jupyter2hashnode/nbconvert/templates/hashnode/conf.json
jupyter2hashnode/nbconvert/templates/hashnode/index.md.j2
jupyter2hashnode-0.1.31.dist-info/entry_points.txt
jupyter2hashnode-0.1.31.dist-info/LICENSE
jupyter2hashnode-0.1.31.dist-info/METADATA
jupyter2hashnode-0.1.31.dist-info/WHEEL
jupyter2hashnode-0.1.31.dist-info/RECORD
