Metadata-Version: 2.1
Name: jupyter2hashnode
Version: 0.1.31
Summary: Export from jupyter notebook into hashnode blog articles
Home-page: https://github.com/tiagopatriciosantos/jupyter2hashnode
License: MIT
Author: Tiago Patricio Santos
Author-email: tiagopatriciosantos@gmail.com
Requires-Python: >=3.8,<4.0
Classifier: License :: OSI Approved :: MIT License
Classifier: Programming Language :: Python :: 3
Classifier: Programming Language :: Python :: 3.8
Classifier: Programming Language :: Python :: 3.9
Classifier: Programming Language :: Python :: 3.10
Classifier: Programming Language :: Python :: 3.11
Provides-Extra: docs
Requires-Dist: Pillow (>=9.4.0,<10.0.0)
Requires-Dist: Sphinx (>=6.1.3,<7.0.0) ; extra == "docs"
Requires-Dist: nbconvert (>=7.2.9,<8.0.0)
Requires-Dist: nbsphinx (>=0.8.12,<0.9.0) ; extra == "docs"
Requires-Dist: python-dotenv (>=0.21.1,<0.22.0)
Requires-Dist: requests (>=2.28.2,<3.0.0)
Requires-Dist: sphinx-rtd-theme (>=1.2.0,<2.0.0) ; extra == "docs"
Requires-Dist: typer[all] (>=0.7.0,<0.8.0)
Project-URL: Documentation, https://jupyter2hashnode.readthedocs.io/en/latest/index.html
